{"trial_id": "0050", "hyperparameters": {"space": [{"class_name": "Int", "config": {"name": "embedding_dim", "default": null, "conditions": [], "min_value": 100, "max_value": 300, "step": 50, "sampling": "linear"}}, {"class_name": "Int", "config": {"name": "lstm_units", "default": null, "conditions": [], "min_value": 64, "max_value": 256, "step": 64, "sampling": "linear"}}, {"class_name": "Float", "config": {"name": "dropout", "default": 0.2, "conditions": [], "min_value": 0.2, "max_value": 0.5, "step": 0.1, "sampling": "linear"}}, {"class_name": "Choice", "config": {"name": "learning_rate", "default": 0.001, "conditions": [], "values": [0.001, 0.0005, 0.0001], "ordered": true}}], "values": {"embedding_dim": 250, "lstm_units": 192, "dropout": 0.30000000000000004, "learning_rate": 0.0005, "tuner/epochs": 30, "tuner/initial_epoch": 10, "tuner/bracket": 3, "tuner/round": 3, "tuner/trial_id": "0048"}}, "metrics": {"metrics": {"accuracy": {"direction": "max", "observations": [{"value": [0.7625047564506531], "step": 17}]}, "loss": {"direction": "min", "observations": [{"value": [0.6992172598838806], "step": 17}]}, "val_accuracy": {"direction": "max", "observations": [{"value": [0.25114503502845764], "step": 17}]}, "val_loss": {"direction": "min", "observations": [{"value": [2.3033905029296875], "step": 17}]}}}, "score": 0.25114503502845764, "best_step": 17, "status": "COMPLETED", "message": null}